[
    {
        "id": 1,
        "name": "Buzo 1",
        "precio": 25.000,
        "img": "/img/buzo1.webp",
        "category":"Oversize"
    },
    {
        "id": 2,
        "name": "Buzo 2",
        "precio": 21.000,
        "img": "/img/buzo2.jpg",
        "category":"Talle Unico"
    },
    {
        "id": 3,
        "name": "Buzo 3",
        "precio": 14.000,
        "img": "/img/buzo3.jpg",
        "category":"Oversize"
    },
    {
        "id": 4,
        "name": "Buzo 4",
        "precio": 13.000,
        "img": "/img/buzo4.jpg",
        "category":"Oversize"
    },
    {
        "id": 5,
        "name": "Buzo 5",
        "precio": 21.000,
        "img": "/img/buzo5.jpg",
        "category":"Talle Unico"
    },
    {
        "id": 6,
        "name": "Buzo 6",
        "precio": 18.000,
        "img": "/img/buzo6.webp",
        "category":"Oversize"
    }
]